mediawiki_scraper/__init__.py
mediawiki_scraper-0.0.0.dist-info/WHEEL
mediawiki_scraper-0.0.0.dist-info/METADATA
mediawiki_scraper-0.0.0.dist-info/RECORD
