Metadata-Version: 2.1
Name: mediawiki-scraper
Version: 0.0.0
Summary: MediaWiki Scraper
Author: Elsie Hupp
Author-email: github@elsiehupp.com
Requires-Python: >=3.8,<4.0
Classifier: Programming Language :: Python :: 3
Classifier: Programming Language :: Python :: 3.10
Classifier: Programming Language :: Python :: 3.8
Classifier: Programming Language :: Python :: 3.9
